teamplify_runner/__init__.py
teamplify_runner/cli.py
teamplify_runner/configurator.py
teamplify_runner/docker-compose.yml
teamplify_runner/mysql.cnf
teamplify_runner/redis.conf
teamplify_runner/utils.py
teamplify_runner/uwsgi_params.conf
teamplify_runner/vhost.conf
teamplify_runner/backup/readme.txt
teamplify-0.10.0.dist-info/LICENSE
teamplify-0.10.0.dist-info/METADATA
teamplify-0.10.0.dist-info/WHEEL
teamplify-0.10.0.dist-info/entry_points.txt
teamplify-0.10.0.dist-info/top_level.txt
teamplify-0.10.0.dist-info/RECORD
