Metadata-Version: 2.1
Name: teamplify
Version: 0.10.0
Summary: Teamplify on-premise runner
Home-page: https://github.com/teamplify/teamplify-runner/
Author: Teamplify
Author-email: support@teamplify.com
License: MIT
Requires-Python: >=3.6
License-File: LICENSE
Requires-Dist: certifi >=2022.12.7
Requires-Dist: click >=5.0
Requires-Dist: requests >=2.28.2
Requires-Dist: sarge >=0.1.4
Provides-Extra: tests
Requires-Dist: flake8 >=3.2.1 ; extra == 'tests'
Requires-Dist: flake8-isort >=2.6.0 ; extra == 'tests'
Requires-Dist: pytest >=2.9.0 ; extra == 'tests'
Requires-Dist: selenium >=4.8.3 ; extra == 'tests'
